bwutils/__init__.py
bwutils/foo.py
bwutils-0.0.1.dist-info/LICENSE
bwutils-0.0.1.dist-info/METADATA
bwutils-0.0.1.dist-info/WHEEL
bwutils-0.0.1.dist-info/RECORD
