Metadata-Version: 2.1
Name: bwutils
Version: 0.0.1
Summary: A set of scripts for LCA related calculations using Brightway framework v 2.4.*
Home-page: https://github.com/rahulrameshnair/bwutils
Author: Rahul Ramesh Nair
Author-email: rahulgenesis@hotmail.com
Requires-Python: >=3.8,<4.0
Classifier: Programming Language :: Python :: 3
Classifier: Programming Language :: Python :: 3.8
Classifier: Programming Language :: Python :: 3.9
Classifier: Programming Language :: Python :: 3.10
Classifier: Programming Language :: Python :: 3.11
Classifier: Programming Language :: Python :: 3.12
Project-URL: Documentation, https://rahulrameshnair.github.io/bwutils/
Project-URL: Repository, https://github.com/rahulrameshnair/bwutils
